ideal_words/__init__.py
ideal_words/ideal_words.py
ideal_words-0.1.0.dist-info/METADATA
ideal_words-0.1.0.dist-info/WHEEL
ideal_words-0.1.0.dist-info/licenses/LICENSE
ideal_words-0.1.0.dist-info/RECORD
