Metadata-Version: 2.4
Name: ideal_words
Version: 0.1.0
Summary: A PyTorch implementation of ideal word computation.
Project-URL: repository, https://github.com/icetube23/ideal_words
Author: icetube23
License-File: LICENSE
Classifier: Development Status :: 4 - Beta
Classifier: Operating System :: OS Independent
Classifier: Programming Language :: Python :: 3
Requires-Python: >=3.10
Requires-Dist: torch
Requires-Dist: tqdm
Provides-Extra: demo
Requires-Dist: open-clip-torch; extra == 'demo'
Provides-Extra: dev
Requires-Dist: pre-commit; extra == 'dev'
Requires-Dist: pytest; extra == 'dev'
Requires-Dist: pytest-cov; extra == 'dev'
Requires-Dist: ruff; extra == 'dev'
